bump_deps_index/__init__.py
bump_deps_index/__main__.py
bump_deps_index/_cli.py
bump_deps_index/_run.py
bump_deps_index/_spec.py
bump_deps_index/py.typed
bump_deps_index/version.py
bump_deps_index/_loaders/__init__.py
bump_deps_index/_loaders/_base.py
bump_deps_index/_loaders/pre_commit_config.py
bump_deps_index/_loaders/pyproject_toml.py
bump_deps_index/_loaders/requirements.py
bump_deps_index/_loaders/script_metadata.py
bump_deps_index/_loaders/setup_cfg.py
bump_deps_index/_loaders/tox_ini.py
bump_deps_index/_loaders/tox_toml.py
bump_deps_index-1.12.0.dist-info/METADATA
bump_deps_index-1.12.0.dist-info/WHEEL
bump_deps_index-1.12.0.dist-info/entry_points.txt
bump_deps_index-1.12.0.dist-info/licenses/LICENSE
bump_deps_index-1.12.0.dist-info/RECORD
