Metadata-Version: 2.4
Name: bump-deps-index
Version: 1.12.0
Summary: Bump your dependencies to latest available from index.
Project-URL: Documentation, https://bump-deps-index.readthedocs.io
Project-URL: Homepage, https://github.com/gaborbernat/bump-deps-index
Project-URL: Source, https://github.com/gaborbernat/bump-deps-index
Project-URL: Tracker, https://github.com/gaborbernat/bump-deps-index/issues
Maintainer-email: Bernát Gábor <gaborjbernat@gmail.com>
License: MIT License
License-File: LICENSE
Keywords: bump,index,pypi,version
Classifier: Development Status :: 5 - Production/Stable
Classifier: Intended Audience :: Developers
Classifier: License :: OSI Approved :: MIT License
Classifier: Operating System :: OS Independent
Classifier: Programming Language :: Python
Classifier: Programming Language :: Python :: 3 :: Only
Classifier: Programming Language :: Python :: 3.11
Classifier: Programming Language :: Python :: 3.12
Classifier: Programming Language :: Python :: 3.13
Classifier: Programming Language :: Python :: 3.14
Classifier: Programming Language :: Python :: Implementation :: CPython
Classifier: Topic :: Software Development :: Libraries :: Python Modules
Requires-Python: >=3.11
Requires-Dist: httpx>=0.28.1
Requires-Dist: packaging>=25
Requires-Dist: pyyaml>=6.0.3
Requires-Dist: truststore>=0.10.4
